troyai/__init__.py
troyai/constants.py
troyai/download.py
troyai/error_helpers.py
troyai/upload.py
troyai-0.0.2.dist-info/LICENSE
troyai-0.0.2.dist-info/METADATA
troyai-0.0.2.dist-info/WHEEL
troyai-0.0.2.dist-info/top_level.txt
troyai-0.0.2.dist-info/RECORD
